Workbook

Sheet P&L Dashboard
A1: Equity Trade P&L Dashboard
A2: Selected-trade P&L analysis: actual aggregate trade outcomes, contributors and learning points. It does not treat trades as one simultaneous portfolio.
A4: Key P&L indicators | F4: Performance quality
A5: Selected trades | B5: =COUNTA('Trade P&L & Stories'!A4:A16) -> 13 | F5: Winning trades | H5: =COUNTIF('Trade P&L & Stories'!E4:E16,">0") -> 8
A6: Total buy value | B6: =SUM('Trade P&L & Stories'!C4:C16) -> 3989961.2 | F6: Losing trades | H6: =COUNTIF('Trade P&L & Stories'!E4:E16,"<0") -> 5
A7: Total sell value | B7: =SUM('Trade P&L & Stories'!D4:D16) -> 4213839.8 | F7: Win rate | H7: =H5/(H5+H6) -> 0.61538462
A8: Realized P&L | B8: ='Trade P&L & Stories'!E17 -> 223878.63 | F8: Profit factor | H8: =B10/ABS(B11) -> 10.938302
A9: Selected-trade return | B9: =B8/B6 -> 0.056110479 | F9: Largest contributor | H9: =INDEX('Trade P&L & Stories'!A4:A16,MATCH(MAX('Trade P&L & Stories'!E4:E16),'Trade P&L & Stories'!E4:E16,0)) -> ZENSARTECH
A10: Gross gains | B10: =SUMIF('Trade P&L & Stories'!E4:E16,">0",'Trade P&L & Stories'!E4:E16) -> 246405.48 | F10: Largest detractor | H10: =INDEX('Trade P&L & Stories'!A4:A16,MATCH(MIN('Trade P&L & Stories'!E4:E16),'Trade P&L & Stories'!E4:E16,0)) -> IRFC
A11: Gross losses | B11: =SUMIF('Trade P&L & Stories'!E4:E16,"<0",'Trade P&L & Stories'!E4:E16) -> -22526.85
A14: P&L by instrument | H14: Key investor takeaways
A15: Symbol | B15: Buy Value | C15: Sell Value | D15: Realized P&L | E15: Return % | F15: Trade Type | H15: • Highest realized P&L contributor: ZENSARTECH; strongest return: AHCL. • The dataset includes both technical and fundamental/thematic ideas, plus banking and IPO trades. • IRFC illustrates a failed breakout and the need for position-size discipline. • RRKABEL and SAGILITY show that an exit reason can differ from the original investment thesis. • P&L check is arithmetic only; transaction-charge allocation and independent broker comparison are not available at trade level.
A16: ='Trade P&L & Stories'!A4 -> ZENSARTECH | B16: ='Trade P&L & Stories'!C4 -> 284200.5 | C16: ='Trade P&L & Stories'!D4 -> 335000 | D16: ='Trade P&L & Stories'!E4 -> 50799.5 | E16: ='Trade P&L & Stories'!F4 -> 0.17874529 | F16: ='Trade P&L & Stories'!H4 -> Technical Analysis
A17: ='Trade P&L & Stories'!A5 -> AHCL | B17: ='Trade P&L & Stories'!C5 -> 93500 | C17: ='Trade P&L & Stories'!D5 -> 143090.13 | D17: ='Trade P&L & Stories'!E5 -> 49590.13 | E17: ='Trade P&L & Stories'!F5 -> 0.53037572 | F17: ='Trade P&L & Stories'!H5 -> Thematic / Fundamental
A18: ='Trade P&L & Stories'!A6 -> MAHABANK | B18: ='Trade P&L & Stories'!C6 -> 408447.1 | C18: ='Trade P&L & Stories'!D6 -> 441733.2 | D18: ='Trade P&L & Stories'!E6 -> 33286.1 | E18: ='Trade P&L & Stories'!F6 -> 0.081494274 | F18: ='Trade P&L & Stories'!H6 -> Fundamental Analysis
A19: ='Trade P&L & Stories'!A7 -> GSFC | B19: ='Trade P&L & Stories'!C7 -> 758510 | C19: ='Trade P&L & Stories'!D7 -> 784940 | D19: ='Trade P&L & Stories'!E7 -> 26430 | E19: ='Trade P&L & Stories'!F7 -> 0.03484463 | F19: ='Trade P&L & Stories'!H7 -> Fundamental + Technical Anal
A20: ='Trade P&L & Stories'!A8 -> UNIONBANK | B20: ='Trade P&L & Stories'!C8 -> 785180.6 | C20: ='Trade P&L & Stories'!D8 -> 810703.1 | D20: ='Trade P&L & Stories'!E8 -> 25522.5 | E20: ='Trade P&L & Stories'!F8 -> 0.032505261 | F20: ='Trade P&L & Stories'!H8 -> Fundamental Analysis
A21: ='Trade P&L & Stories'!A9 -> SOUTHBANK | B21: ='Trade P&L & Stories'!C9 -> 203140 | C21: ='Trade P&L & Stories'!D9 -> 225122 | D21: ='Trade P&L & Stories'!E9 -> 21982 | E21: ='Trade P&L & Stories'!F9 -> 0.10821109 | F21: ='Trade P&L & Stories'!H9 -> Fundamental Analysis
A22: ='Trade P&L & Stories'!A10 -> LUXIND | B22: ='Trade P&L & Stories'!C10 -> 171950 | C22: ='Trade P&L & Stories'!D10 -> 192000 | D22: ='Trade P&L & Stories'!E10 -> 20050 | E22: ='Trade P&L & Stories'!F10 -> 0.11660366 | F22: ='Trade P&L & Stories'!H10 -> Technical Analysis
A23: ='Trade P&L & Stories'!A11 -> BBTC | B23: ='Trade P&L & Stories'!C11 -> 308518.75 | C23: ='Trade P&L & Stories'!D11 -> 327264 | D23: ='Trade P&L & Stories'!E11 -> 18745.25 | E23: ='Trade P&L & Stories'!F11 -> 0.060758868 | F23: ='Trade P&L & Stories'!H11 -> Technical Analysis
A24: ='Trade P&L & Stories'!A12 -> IRFC | B24: ='Trade P&L & Stories'!C12 -> 89974.2 | C24: ='Trade P&L & Stories'!D12 -> 83815.05 | D24: ='Trade P&L & Stories'!E12 -> -6159.15 | E24: ='Trade P&L & Stories'!F12 -> -0.068454624 | F24: ='Trade P&L & Stories'!H12 -> Technical Analysis | J24: Symbol | K24: P&L
A25: ='Trade P&L & Stories'!A13 -> RRKABEL | B25: ='Trade P&L & Stories'!C13 -> 129980 | C25: ='Trade P&L & Stories'!D13 -> 124696 | D25: ='Trade P&L & Stories'!E13 -> -5284 | E25: ='Trade P&L & Stories'!F13 -> -0.040652408 | F25: ='Trade P&L & Stories'!H13 -> Fundamental Analysis | J25: ='Trade P&L & Stories'!A4 -> ZENSARTECH | K25: ='Trade P&L & Stories'!E4 -> 50799.5
A26: ='Trade P&L & Stories'!A14 -> SAGILITY | B26: ='Trade P&L & Stories'!C14 -> 99000 | C26: ='Trade P&L & Stories'!D14 -> 94094 | D26: ='Trade P&L & Stories'!E14 -> -4906 | E26: ='Trade P&L & Stories'!F14 -> -0.049555556 | F26: ='Trade P&L & Stories'!H14 -> Other | J26: ='Trade P&L & Stories'!A5 -> AHCL | K26: ='Trade P&L & Stories'!E5 -> 49590.13
A27: ='Trade P&L & Stories'!A15 -> MAMATA | B27: ='Trade P&L & Stories'!C15 -> 559850 | C27: ='Trade P&L & Stories'!D15 -> 555729.8 | D27: ='Trade P&L & Stories'!E15 -> -4120.2 | E27: ='Trade P&L & Stories'!F15 -> -0.0073594713 | F27: ='Trade P&L & Stories'!H15 -> IPO | J27: ='Trade P&L & Stories'!A6 -> MAHABANK | K27: ='Trade P&L & Stories'!E6 -> 33286.1
A28: ='Trade P&L & Stories'!A16 -> JKPAPER | B28: ='Trade P&L & Stories'!C16 -> 97710 | C28: ='Trade P&L & Stories'!D16 -> 95652.5 | D28: ='Trade P&L & Stories'!E16 -> -2057.5 | E28: ='Trade P&L & Stories'!F16 -> -0.02105721 | F28: ='Trade P&L & Stories'!H16 -> Fundamental | J28: ='Trade P&L & Stories'!A7 -> GSFC | K28: ='Trade P&L & Stories'!E7 -> 26430
J29: ='Trade P&L & Stories'!A8 -> UNIONBANK | K29: ='Trade P&L & Stories'!E8 -> 25522.5
J30: ='Trade P&L & Stories'!A9 -> SOUTHBANK | K30: ='Trade P&L & Stories'!E9 -> 21982
J31: ='Trade P&L & Stories'!A10 -> LUXIND | K31: ='Trade P&L & Stories'!E10 -> 20050
J32: ='Trade P&L & Stories'!A11 -> BBTC | K32: ='Trade P&L & Stories'!E11 -> 18745.25
J33: ='Trade P&L & Stories'!A12 -> IRFC | K33: ='Trade P&L & Stories'!E12 -> -6159.15
J34: ='Trade P&L & Stories'!A13 -> RRKABEL | K34: ='Trade P&L & Stories'!E13 -> -5284
J35: ='Trade P&L & Stories'!A14 -> SAGILITY | K35: ='Trade P&L & Stories'!E14 -> -4906
J36: ='Trade P&L & Stories'!A15 -> MAMATA | K36: ='Trade P&L & Stories'!E15 -> -4120.2
J37: ='Trade P&L & Stories'!A16 -> JKPAPER | K37: ='Trade P&L & Stories'!E16 -> -2057.5

Sheet Trade P&L & Stories
A1: Personal Equity Trade P&L & Investment Stories
A3: Symbol | B3: Quantity | C3: Buy Value | D3: Sell Value | E3: Realized P&L | F3: Return % | G3: P&L Contribution | H3: Trade Type | I3: Investment thesis / entry rationale | J3: Exit / risk lesson | K3: P&L Check
A4: ZENSARTECH | B4: 450 | C4: 284200.5 | D4: 335000 | E4: 50799.5 | F4: =E4/C4 -> 0.17874529 | G4: =E4/$E$17 -> 0.22690643 | H4: Technical Analysis | I4: Flag-and-pole technical pattern. | J4: Technical setup worked; retain technical discipline. | K4: =D4-C4 -> 50799.5
A5: AHCL | B5: 1000 | C5: 93500 | D5: 143090.13 | E5: 49590.13 | F5: =E5/C5 -> 0.53037572 | G5: =E5/$E$17 -> 0.22150453 | H5: Thematic / Fundamental | I5: API/pharma idea: Dolo/paracetamol production and China-alternative thesis. | J5: Theme and thesis supported a strong outcome. | K5: =D5-C5 -> 49590.13
A6: MAHABANK | B6: 9870 | C6: 408447.1 | D6: 441733.2 | E6: 33286.1 | F6: =E6/C6 -> 0.081494274 | G6: =E6/$E$17 -> 0.14867922 | H6: Fundamental Analysis | I6: Undervalued PSU bank during broader government-bank rally. | J6: Value opportunity where profits improved before price fully reflected it. | K6: =D6-C6 -> 33286.1
A7: GSFC | B7: 3280 | C7: 758510 | D7: 784940 | E7: 26430 | F7: =E7/C7 -> 0.03484463 | G7: =E7/$E$17 -> 0.11805504 | H7: Fundamental + Technical Anal | I7: Zero-debt government company viewed as undervalued. | J7: Fundamental valuation opportunity. | K7: =D7-C7 -> 26430
A8: UNIONBANK | B8: 7443 | C8: 785180.6 | D8: 810703.1 | E8: 25522.5 | F8: =E8/C8 -> 0.032505261 | G8: =E8/$E$17 -> 0.1140015 | H8: Fundamental Analysis | I8: Undervalued PSU bank during broader government-bank rally. | J8: Monitor sector momentum and valuation. | K8: =D8-C8 -> 25522.5
A9: SOUTHBANK | B9: 5700 | C9: 203140 | D9: 225122 | E9: 21982 | F9: =E9/C9 -> 0.10821109 | G9: =E9/$E$17 -> 0.098187129 | H9: Fundamental Analysis | I9: Bank-sector opportunity. | J9: Monitor sector momentum and valuation. | K9: =D9-C9 -> 21982
A10: LUXIND | B10: 100 | C10: 171950 | D10: 192000 | E10: 20050 | F10: =E10/C10 -> 0.11660366 | G10: =E10/$E$17 -> 0.089557454 | H10: Technical Analysis | I10: Technical trade. | J10: Use chart signals and exit discipline. | K10: =D10-C10 -> 20050
A11: BBTC | B11: 150 | C11: 308518.75 | D11: 327264 | E11: 18745.25 | F11: =E11/C11 -> 0.060758868 | G11: =E11/$E$17 -> 0.083729519 | H11: Technical Analysis | I11: Technical trade using chart and volume. | J11: Volume confirmation was part of entry process. | K11: =D11-C11 -> 18745.25
A12: IRFC | B12: 2607 | C12: 89974.2 | D12: 83815.05 | E12: -6159.15 | F12: =E12/C12 -> -0.068454624 | G12: =E12/$E$17 -> -0.027511112 | H12: Technical Analysis | I12: Chart-led swing trade / technical breakout. | J12: Breakout failed; avoid full-capital deployment on one chart view. | K12: =D12-C12 -> -6159.15
A13: RRKABEL | B13: 97 | C13: 129980 | D13: 124696 | E13: -5284 | F13: =E13/C13 -> -0.040652408 | G13: =E13/$E$17 -> -0.023602074 | H13: Fundamental Analysis | I13: Fundamental thesis was positive. | J13: Sold due to personal financial need; outcome did not invalidate thesis. | K13: =D13-C13 -> -5284
A14: SAGILITY | B14: 2200 | C14: 99000 | D14: 94094 | E14: -4906 | F14: =E14/C14 -> -0.049555556 | G14: =E14/$E$17 -> -0.021913659 | H14: Other | I14: Personal conviction in the idea. | J14: Patience and holding-period discipline needed. | K14: =D14-C14 -> -4906
A15: MAMATA | B15: 1200 | C15: 559850 | D15: 555729.8 | E15: -4120.2 | F15: =E15/C15 -> -0.0073594713 | G15: =E15/$E$17 -> -0.018403722 | H15: IPO | I15: IPO-based investment idea. | J15: Post-listing performance did not meet expectations. | K15: =D15-C15 -> -4120.2
A16: JKPAPER | B16: 300 | C16: 97710 | D16: 95652.5 | E16: -2057.5 | F16: =E16/C16 -> -0.02105721 | G16: =E16/$E$17 -> -0.0091902474 | H16: Fundamental | I16: Bullish company/backstory thesis. | J16: Stock did not perform as expected; review thesis and catalysts. | K16: =D16-C16 -> -2057.5
A17: Selected-trade total | E17: =SUM(E4:E16) -> 223878.63 | F17: =E17/SUM(C4:C16) -> 0.056110479 | G17: =SUM(G4:G16) -> 1
A20: Data note: Buy Value, Sell Value and Realized P&L are the actual aggregate values provided for each selected trade. The P&L check validates only that Sell Value − Buy Value equals stated Realized P&L; it is not an independent broker reconciliation.

Sheet Risk & Controls
A1: Risk & Controls Review
A3: Investment process and risk lessons
A4: Topic | B4: Approach / learning
A5: Strategy | B5: Swing/positional equity trading using technical analysis, fundamental/value ideas, momentum, volume, RSI, chart patterns and themes.
A6: Position sizing | B6: Normal stated range: approximately 35–50% of capital; avoid full-capital concentration.
A7: Technical lesson | B7: A breakout can fail; use confirmation and sizing limits rather than relying on a single chart view.
A8: Fundamental lesson | B8: A correct thesis can still have an unfavourable outcome or require an exit for personal liquidity.
A9: Patience lesson | B9: Sagility reflects the need to define holding period and review triggers.
A13: Conclusion
A14: I analysed selected personal equity trades in Excel, calculated realized P&L and trade-level returns, identified leading contributors and detractors, and documented the investment thesis and lessons behind each outcome. I also added simple P&L validation checks to distinguish arithmetic consistency from an independent reconciliation. The project demonstrates my interest in markets, investment analysis, P&L attribution and disciplined post-trade review.
